{"1":{"id":1,"category":"nonCraftable","ingridients":[{"itemId":637,"ratio":1.0,"quantity":1,"maxLevelRequired":false,"title":"637"}],"softCurrencyFee":0,"hardCurrencyFee":0,"unlockLevel":1,"iap":"","resultItem":0},"2":{"id":2,"category":"nonCraftable","ingridients":[],"softCurrencyFee":0,"hardCurrencyFee":0,"unlockLevel":1,"iap":"","resultItem":0},"3":{"id":3,"category":"nonCraftable","ingridients":[],"softCurrencyFee":0,"hardCurrencyFee":0,"unlockLevel":1,"iap":"","resultItem":0},"4":{"id":4,"category":"nonCraftable","ingridients":[],"softCurrencyFee":0,"hardCurrencyFee":0,"unlockLevel":1,"iap":"","resultItem":0},"7":{"id":7,"category":"equipment","ingridients":[{"itemId":865,"ratio":1.0,"quantity":23,"maxLevelRequired":false,"title":"865"},{"itemId":869,"ratio":1.0,"quantity":23,"maxLevelRequired":false,"title":"869"}],"softCurrencyFee":500,"hardCurrencyFee":0,"unlockLevel":1,"iap":"","resultItem":1437},"8":{"id":8,"category":"equipment","ingridients":[{"itemId":866,"ratio":1.0,"quantity":23,"maxLevelRequired":false,"title":"866"},{"itemId":869,"ratio":1.0,"quantity":23,"maxLevelRequired":false,"title":"869"}],"softCurrencyFee":500,"hardCurrencyFee":0,"unlockLevel":1,"iap":"","resultItem":1439},"9":{"id":9,"category":"equipment","ingridients":[{"itemId":867,"ratio":1.0,"quantity":23,"maxLevelRequired":false,"title":"867"},{"itemId":868,"ratio":1.0,"quantity":23,"maxLevelRequired":false,"title":"868"}],"softCurrencyFee":500,"hardCurrencyFee":0,"unlockLevel":1,"iap":"","resultItem":1441},"10":{"id":10,"category":"equipment","ingridients":[{"itemId":865,"ratio":1.0,"quantity":23,"maxLevelRequired":false,"title":"865"},{"itemId":868,"ratio":1.0,"quantity":23,"maxLevelRequired":false,"title":"868"}],"softCurrencyFee":500,"hardCurrencyFee":0,"unlockLevel":1,"iap":"","resultItem":1442},"11":{"id":11,"category":"equipment","ingridients":[{"itemId":867,"ratio":1.0,"quantity":23,"maxLevelRequired":false,"title":"867"},{"itemId":868,"ratio":1.0,"quantity":23,"maxLevelRequired":false,"title":"868"}],"softCurrencyFee":500,"hardCurrencyFee":0,"unlockLevel":1,"iap":"","resultItem":1443},"12":{"id":12,"category":"equipment","ingridients":[{"itemId":866,"ratio":1.0,"quantity":23,"maxLevelRequired":false,"title":"866"},{"itemId":869,"ratio":1.0,"quantity":23,"maxLevelRequired":false,"title":"869"}],"softCurrencyFee":500,"hardCurrencyFee":0,"unlockLevel":1,"iap":"","resultItem":1445},"13":{"id":13,"category":"equipment","ingridients":[{"itemId":866,"ratio":1.0,"quantity":23,"maxLevelRequired":false,"title":"866"},{"itemId":868,"ratio":1.0,"quantity":23,"maxLevelRequired":false,"title":"868"}],"softCurrencyFee":500,"hardCurrencyFee":0,"unlockLevel":1,"iap":"","resultItem":1446},"14":{"id":14,"category":"equipment","ingridients":[{"itemId":865,"ratio":1.0,"quantity":23,"maxLevelRequired":false,"title":"865"},{"itemId":867,"ratio":1.0,"quantity":23,"maxLevelRequired":false,"title":"867"}],"softCurrencyFee":500,"hardCurrencyFee":0,"unlockLevel":1,"iap":"","resultItem":1448},"15":{"id":15,"category":"equipment","ingridients":[{"itemId":866,"ratio":1.0,"quantity":23,"maxLevelRequired":false,"title":"866"},{"itemId":868,"ratio":1.0,"quantity":23,"maxLevelRequired":false,"title":"868"}],"softCurrencyFee":500,"hardCurrencyFee":0,"unlockLevel":1,"iap":"","resultItem":1450},"16":{"id":16,"category":"equipment","ingridients":[{"itemId":867,"ratio":1.0,"quantity":23,"maxLevelRequired":false,"title":"867"},{"itemId":869,"ratio":1.0,"quantity":23,"maxLevelRequired":false,"title":"869"}],"softCurrencyFee":500,"hardCurrencyFee":0,"unlockLevel":1,"iap":"","resultItem":1451},"17":{"id":17,"category":"equipment","ingridients":[{"itemId":865,"ratio":1.0,"quantity":23,"maxLevelRequired":false,"title":"865"},{"itemId":867,"ratio":1.0,"quantity":23,"maxLevelRequired":false,"title":"867"}],"softCurrencyFee":500,"hardCurrencyFee":0,"unlockLevel":1,"iap":"","resultItem":1452},"18":{"id":18,"category":"equipment","ingridients":[{"itemId":865,"ratio":1.0,"quantity":23,"maxLevelRequired":false,"title":"865"},{"itemId":869,"ratio":1.0,"quantity":23,"maxLevelRequired":false,"title":"869"}],"softCurrencyFee":500,"hardCurrencyFee":0,"unlockLevel":1,"iap":"","resultItem":1453},"19":{"id":19,"category":"equipment","ingridients":[{"itemId":866,"ratio":1.0,"quantity":23,"maxLevelRequired":false,"title":"866"},{"itemId":868,"ratio":1.0,"quantity":23,"maxLevelRequired":false,"title":"868"}],"softCurrencyFee":500,"hardCurrencyFee":0,"unlockLevel":1,"iap":"","resultItem":1454},"20":{"id":20,"category":"equipment","ingridients":[{"itemId":867,"ratio":1.0,"quantity":23,"maxLevelRequired":false,"title":"867"},{"itemId":869,"ratio":1.0,"quantity":23,"maxLevelRequired":false,"title":"869"}],"softCurrencyFee":500,"hardCurrencyFee":0,"unlockLevel":1,"iap":"","resultItem":1457},"21":{"id":21,"category":"equipment","ingridients":[{"itemId":865,"ratio":1.0,"quantity":23,"maxLevelRequired":false,"title":"865"},{"itemId":866,"ratio":1.0,"quantity":23,"maxLevelRequired":false,"title":"866"}],"softCurrencyFee":500,"hardCurrencyFee":0,"unlockLevel":1,"iap":"","resultItem":1458},"22":{"id":22,"category":"equipment","ingridients":[{"itemId":867,"ratio":1.0,"quantity":23,"maxLevelRequired":false,"title":"867"},{"itemId":869,"ratio":1.0,"quantity":23,"maxLevelRequired":false,"title":"869"}],"softCurrencyFee":500,"hardCurrencyFee":0,"unlockLevel":1,"iap":"","resultItem":1460},"23":{"id":23,"category":"equipment","ingridients":[{"itemId":865,"ratio":1.0,"quantity":23,"maxLevelRequired":false,"title":"865"},{"itemId":866,"ratio":1.0,"quantity":23,"maxLevelRequired":false,"title":"866"}],"softCurrencyFee":500,"hardCurrencyFee":0,"unlockLevel":1,"iap":"","resultItem":1417},"24":{"id":24,"category":"equipment","ingridients":[{"itemId":866,"ratio":1.0,"quantity":23,"maxLevelRequired":false,"title":"866"},{"itemId":867,"ratio":1.0,"quantity":23,"maxLevelRequired":false,"title":"867"}],"softCurrencyFee":500,"hardCurrencyFee":0,"unlockLevel":1,"iap":"","resultItem":1418},"25":{"id":25,"category":"equipment","ingridients":[{"itemId":867,"ratio":1.0,"quantity":23,"maxLevelRequired":false,"title":"867"},{"itemId":868,"ratio":1.0,"quantity":23,"maxLevelRequired":false,"title":"868"}],"softCurrencyFee":500,"hardCurrencyFee":0,"unlockLevel":1,"iap":"","resultItem":1419},"26":{"id":26,"category":"equipment","ingridients":[{"itemId":868,"ratio":1.0,"quantity":23,"maxLevelRequired":false,"title":"868"},{"itemId":869,"ratio":1.0,"quantity":23,"maxLevelRequired":false,"title":"869"}],"softCurrencyFee":500,"hardCurrencyFee":0,"unlockLevel":1,"iap":"","resultItem":1422},"27":{"id":27,"category":"equipment","ingridients":[{"itemId":865,"ratio":1.0,"quantity":23,"maxLevelRequired":false,"title":"865"},{"itemId":867,"ratio":1.0,"quantity":23,"maxLevelRequired":false,"title":"867"}],"softCurrencyFee":500,"hardCurrencyFee":0,"unlockLevel":1,"iap":"","resultItem":1423},"28":{"id":28,"category":"equipment","ingridients":[{"itemId":865,"ratio":1.0,"quantity":23,"maxLevelRequired":false,"title":"865"},{"itemId":868,"ratio":1.0,"quantity":23,"maxLevelRequired":false,"title":"868"}],"softCurrencyFee":500,"hardCurrencyFee":0,"unlockLevel":1,"iap":"","resultItem":1424},"29":{"id":29,"category":"equipment","ingridients":[{"itemId":865,"ratio":1.0,"quantity":23,"maxLevelRequired":false,"title":"865"},{"itemId":869,"ratio":1.0,"quantity":23,"maxLevelRequired":false,"title":"869"}],"softCurrencyFee":500,"hardCurrencyFee":0,"unlockLevel":1,"iap":"","resultItem":1425},"30":{"id":30,"category":"equipment","ingridients":[{"itemId":866,"ratio":1.0,"quantity":23,"maxLevelRequired":false,"title":"866"},{"itemId":868,"ratio":1.0,"quantity":23,"maxLevelRequired":false,"title":"868"}],"softCurrencyFee":500,"hardCurrencyFee":0,"unlockLevel":1,"iap":"","resultItem":1426},"31":{"id":31,"category":"equipment","ingridients":[{"itemId":866,"ratio":1.0,"quantity":23,"maxLevelRequired":false,"title":"866"},{"itemId":869,"ratio":1.0,"quantity":23,"maxLevelRequired":false,"title":"869"}],"softCurrencyFee":500,"hardCurrencyFee":0,"unlockLevel":1,"iap":"","resultItem":1427},"32":{"id":32,"category":"equipment","ingridients":[{"itemId":867,"ratio":1.0,"quantity":23,"maxLevelRequired":false,"title":"867"},{"itemId":869,"ratio":1.0,"quantity":23,"maxLevelRequired":false,"title":"869"}],"softCurrencyFee":500,"hardCurrencyFee":0,"unlockLevel":1,"iap":"","resultItem":1428},"33":{"id":33,"category":"equipment","ingridients":[{"itemId":865,"ratio":1.0,"quantity":23,"maxLevelRequired":false,"title":"865"},{"itemId":867,"ratio":1.0,"quantity":23,"maxLevelRequired":false,"title":"867"}],"softCurrencyFee":500,"hardCurrencyFee":0,"unlockLevel":1,"iap":"","resultItem":1431},"34":{"id":34,"category":"equipment","ingridients":[{"itemId":866,"ratio":1.0,"quantity":23,"maxLevelRequired":false,"title":"866"},{"itemId":869,"ratio":1.0,"quantity":23,"maxLevelRequired":false,"title":"869"}],"softCurrencyFee":500,"hardCurrencyFee":0,"unlockLevel":1,"iap":"","resultItem":1433},"35":{"id":35,"category":"equipment","ingridients":[{"itemId":865,"ratio":1.0,"quantity":23,"maxLevelRequired":false,"title":"865"},{"itemId":868,"ratio":1.0,"quantity":23,"maxLevelRequired":false,"title":"868"}],"softCurrencyFee":500,"hardCurrencyFee":0,"unlockLevel":1,"iap":"","resultItem":1434},"36":{"id":36,"category":"equipment","ingridients":[{"itemId":866,"ratio":1.0,"quantity":23,"maxLevelRequired":false,"title":"866"},{"itemId":868,"ratio":1.0,"quantity":23,"maxLevelRequired":false,"title":"868"}],"softCurrencyFee":500,"hardCurrencyFee":0,"unlockLevel":1,"iap":"","resultItem":1436},"37":{"id":37,"category":"equipment","ingridients":[{"itemId":866,"ratio":1.0,"quantity":596,"maxLevelRequired":false,"title":"866"}],"softCurrencyFee":500,"hardCurrencyFee":0,"unlockLevel":1,"iap":"","resultItem":682},"38":{"id":38,"category":"equipment","ingridients":[{"itemId":865,"ratio":1.0,"quantity":1,"maxLevelRequired":false,"title":"865"},{"itemId":866,"ratio":1.0,"quantity":1,"maxLevelRequired":false,"title":"866"}],"softCurrencyFee":500,"hardCurrencyFee":0,"unlockLevel":1,"iap":"","resultItem":1607},"39":{"id":39,"category":"equipment","ingridients":[{"itemId":866,"ratio":1.0,"quantity":1,"maxLevelRequired":false,"title":"866"},{"itemId":867,"ratio":1.0,"quantity":1,"maxLevelRequired":false,"title":"867"}],"softCurrencyFee":500,"hardCurrencyFee":0,"unlockLevel":1,"iap":"","resultItem":1608},"40":{"id":40,"category":"equipment","ingridients":[{"itemId":867,"ratio":1.0,"quantity":1,"maxLevelRequired":false,"title":"867"},{"itemId":868,"ratio":1.0,"quantity":1,"maxLevelRequired":false,"title":"868"}],"softCurrencyFee":500,"hardCurrencyFee":0,"unlockLevel":1,"iap":"","resultItem":1610},"41":{"id":41,"category":"equipment","ingridients":[{"itemId":865,"ratio":1.0,"quantity":13,"maxLevelRequired":false,"title":"865"},{"itemId":866,"ratio":1.0,"quantity":13,"maxLevelRequired":false,"title":"866"}],"softCurrencyFee":500,"hardCurrencyFee":0,"unlockLevel":1,"iap":"","resultItem":1611},"42":{"id":42,"category":"equipment","ingridients":[{"itemId":866,"ratio":1.0,"quantity":13,"maxLevelRequired":false,"title":"866"},{"itemId":867,"ratio":1.0,"quantity":13,"maxLevelRequired":false,"title":"867"}],"softCurrencyFee":500,"hardCurrencyFee":0,"unlockLevel":1,"iap":"","resultItem":1613},"43":{"id":43,"category":"equipment","ingridients":[{"itemId":867,"ratio":1.0,"quantity":13,"maxLevelRequired":false,"title":"867"},{"itemId":868,"ratio":1.0,"quantity":13,"maxLevelRequired":false,"title":"868"}],"softCurrencyFee":500,"hardCurrencyFee":0,"unlockLevel":1,"iap":"","resultItem":1615},"44":{"id":44,"category":"equipment","ingridients":[{"itemId":868,"ratio":1.0,"quantity":13,"maxLevelRequired":false,"title":"868"},{"itemId":869,"ratio":1.0,"quantity":13,"maxLevelRequired":false,"title":"869"}],"softCurrencyFee":500,"hardCurrencyFee":0,"unlockLevel":1,"iap":"","resultItem":1616},"46":{"id":46,"category":"equipment","ingridients":[{"itemId":865,"ratio":1.0,"quantity":16,"maxLevelRequired":false,"title":"865"},{"itemId":866,"ratio":1.0,"quantity":16,"maxLevelRequired":false,"title":"866"}],"softCurrencyFee":500,"hardCurrencyFee":0,"unlockLevel":1,"iap":"","resultItem":1623},"47":{"id":47,"category":"equipment","ingridients":[{"itemId":866,"ratio":1.0,"quantity":16,"maxLevelRequired":false,"title":"866"},{"itemId":867,"ratio":1.0,"quantity":16,"maxLevelRequired":false,"title":"867"}],"softCurrencyFee":500,"hardCurrencyFee":0,"unlockLevel":1,"iap":"","resultItem":1626},"48":{"id":48,"category":"equipment","ingridients":[{"itemId":867,"ratio":1.0,"quantity":16,"maxLevelRequired":false,"title":"867"},{"itemId":868,"ratio":1.0,"quantity":16,"maxLevelRequired":false,"title":"868"}],"softCurrencyFee":500,"hardCurrencyFee":0,"unlockLevel":1,"iap":"","resultItem":1627},"49":{"id":49,"category":"equipment","ingridients":[{"itemId":868,"ratio":1.0,"quantity":16,"maxLevelRequired":false,"title":"868"},{"itemId":869,"ratio":1.0,"quantity":16,"maxLevelRequired":false,"title":"869"}],"softCurrencyFee":500,"hardCurrencyFee":0,"unlockLevel":1,"iap":"","resultItem":1628},"50":{"id":50,"category":"equipment","ingridients":[{"itemId":865,"ratio":1.0,"quantity":14,"maxLevelRequired":false,"title":"865"},{"itemId":866,"ratio":1.0,"quantity":14,"maxLevelRequired":false,"title":"866"}],"softCurrencyFee":500,"hardCurrencyFee":0,"unlockLevel":1,"iap":"","resultItem":1617},"51":{"id":51,"category":"equipment","ingridients":[{"itemId":866,"ratio":1.0,"quantity":14,"maxLevelRequired":false,"title":"866"},{"itemId":867,"ratio":1.0,"quantity":14,"maxLevelRequired":false,"title":"867"}],"softCurrencyFee":500,"hardCurrencyFee":0,"unlockLevel":1,"iap":"","resultItem":1618},"52":{"id":52,"category":"equipment","ingridients":[{"itemId":867,"ratio":1.0,"quantity":14,"maxLevelRequired":false,"title":"867"},{"itemId":868,"ratio":1.0,"quantity":14,"maxLevelRequired":false,"title":"868"}],"softCurrencyFee":500,"hardCurrencyFee":0,"unlockLevel":1,"iap":"","resultItem":1620},"53":{"id":53,"category":"equipment","ingridients":[{"itemId":868,"ratio":1.0,"quantity":14,"maxLevelRequired":false,"title":"868"},{"itemId":869,"ratio":1.0,"quantity":14,"maxLevelRequired":false,"title":"869"}],"softCurrencyFee":500,"hardCurrencyFee":0,"unlockLevel":1,"iap":"","resultItem":1622},"54":{"id":54,"category":"equipment","ingridients":[{"itemId":865,"ratio":1.0,"quantity":15,"maxLevelRequired":false,"title":"865"},{"itemId":866,"ratio":1.0,"quantity":15,"maxLevelRequired":false,"title":"866"}],"softCurrencyFee":500,"hardCurrencyFee":0,"unlockLevel":1,"iap":"","resultItem":1629},"55":{"id":55,"category":"equipment","ingridients":[{"itemId":866,"ratio":1.0,"quantity":15,"maxLevelRequired":false,"title":"866"},{"itemId":867,"ratio":1.0,"quantity":15,"maxLevelRequired":false,"title":"867"}],"softCurrencyFee":500,"hardCurrencyFee":0,"unlockLevel":1,"iap":"","resultItem":1630},"56":{"id":56,"category":"equipment","ingridients":[{"itemId":867,"ratio":1.0,"quantity":15,"maxLevelRequired":false,"title":"867"},{"itemId":868,"ratio":1.0,"quantity":15,"maxLevelRequired":false,"title":"868"}],"softCurrencyFee":500,"hardCurrencyFee":0,"unlockLevel":1,"iap":"","resultItem":1632},"57":{"id":57,"category":"equipment","ingridients":[{"itemId":868,"ratio":1.0,"quantity":15,"maxLevelRequired":false,"title":"868"},{"itemId":869,"ratio":1.0,"quantity":15,"maxLevelRequired":false,"title":"869"}],"softCurrencyFee":500,"hardCurrencyFee":0,"unlockLevel":1,"iap":"","resultItem":1633},"58":{"id":58,"category":"equipment","ingridients":[{"itemId":865,"ratio":1.0,"quantity":18,"maxLevelRequired":false,"title":"865"},{"itemId":866,"ratio":1.0,"quantity":18,"maxLevelRequired":false,"title":"866"}],"softCurrencyFee":500,"hardCurrencyFee":0,"unlockLevel":1,"iap":"","resultItem":1576},"59":{"id":59,"category":"equipment","ingridients":[{"itemId":866,"ratio":1.0,"quantity":18,"maxLevelRequired":false,"title":"866"},{"itemId":867,"ratio":1.0,"quantity":18,"maxLevelRequired":false,"title":"867"}],"softCurrencyFee":500,"hardCurrencyFee":0,"unlockLevel":1,"iap":"","resultItem":1577},"60":{"id":60,"category":"equipment","ingridients":[{"itemId":867,"ratio":1.0,"quantity":18,"maxLevelRequired":false,"title":"867"},{"itemId":868,"ratio":1.0,"quantity":18,"maxLevelRequired":false,"title":"868"}],"softCurrencyFee":500,"hardCurrencyFee":0,"unlockLevel":1,"iap":"","resultItem":1578},"61":{"id":61,"category":"equipment","ingridients":[{"itemId":868,"ratio":1.0,"quantity":18,"maxLevelRequired":false,"title":"868"},{"itemId":869,"ratio":1.0,"quantity":18,"maxLevelRequired":false,"title":"869"}],"softCurrencyFee":500,"hardCurrencyFee":0,"unlockLevel":1,"iap":"","resultItem":1579},"62":{"id":62,"category":"equipment","ingridients":[{"itemId":865,"ratio":1.0,"quantity":18,"maxLevelRequired":false,"title":"865"},{"itemId":867,"ratio":1.0,"quantity":18,"maxLevelRequired":false,"title":"867"}],"softCurrencyFee":500,"hardCurrencyFee":0,"unlockLevel":1,"iap":"","resultItem":1581},"63":{"id":63,"category":"equipment","ingridients":[{"itemId":865,"ratio":1.0,"quantity":18,"maxLevelRequired":false,"title":"865"},{"itemId":868,"ratio":1.0,"quantity":18,"maxLevelRequired":false,"title":"868"}],"softCurrencyFee":500,"hardCurrencyFee":0,"unlockLevel":1,"iap":"","resultItem":1582},"64":{"id":64,"category":"equipment","ingridients":[{"itemId":865,"ratio":1.0,"quantity":18,"maxLevelRequired":false,"title":"865"},{"itemId":869,"ratio":1.0,"quantity":18,"maxLevelRequired":false,"title":"869"}],"softCurrencyFee":500,"hardCurrencyFee":0,"unlockLevel":1,"iap":"","resultItem":1584},"65":{"id":65,"category":"equipment","ingridients":[{"itemId":866,"ratio":1.0,"quantity":18,"maxLevelRequired":false,"title":"866"},{"itemId":868,"ratio":1.0,"quantity":18,"maxLevelRequired":false,"title":"868"}],"softCurrencyFee":500,"hardCurrencyFee":0,"unlockLevel":1,"iap":"","resultItem":1585},"66":{"id":66,"category":"equipment","ingridients":[{"itemId":866,"ratio":1.0,"quantity":18,"maxLevelRequired":false,"title":"866"},{"itemId":869,"ratio":1.0,"quantity":18,"maxLevelRequired":false,"title":"869"}],"softCurrencyFee":500,"hardCurrencyFee":0,"unlockLevel":1,"iap":"","resultItem":1587},"67":{"id":67,"category":"equipment","ingridients":[{"itemId":867,"ratio":1.0,"quantity":18,"maxLevelRequired":false,"title":"867"},{"itemId":869,"ratio":1.0,"quantity":18,"maxLevelRequired":false,"title":"869"}],"softCurrencyFee":500,"hardCurrencyFee":0,"unlockLevel":1,"iap":"","resultItem":1588},"68":{"id":68,"category":"equipment","ingridients":[{"itemId":865,"ratio":1.0,"quantity":18,"maxLevelRequired":false,"title":"865"},{"itemId":867,"ratio":1.0,"quantity":18,"maxLevelRequired":false,"title":"867"}],"softCurrencyFee":500,"hardCurrencyFee":0,"unlockLevel":1,"iap":"","resultItem":1590},"69":{"id":69,"category":"equipment","ingridients":[{"itemId":866,"ratio":1.0,"quantity":18,"maxLevelRequired":false,"title":"866"},{"itemId":869,"ratio":1.0,"quantity":18,"maxLevelRequired":false,"title":"869"}],"softCurrencyFee":500,"hardCurrencyFee":0,"unlockLevel":1,"iap":"","resultItem":1592},"70":{"id":70,"category":"equipment","ingridients":[{"itemId":865,"ratio":1.0,"quantity":18,"maxLevelRequired":false,"title":"865"},{"itemId":868,"ratio":1.0,"quantity":18,"maxLevelRequired":false,"title":"868"}],"softCurrencyFee":500,"hardCurrencyFee":0,"unlockLevel":1,"iap":"","resultItem":1594},"71":{"id":71,"category":"equipment","ingridients":[{"itemId":866,"ratio":1.0,"quantity":18,"maxLevelRequired":false,"title":"866"},{"itemId":868,"ratio":1.0,"quantity":18,"maxLevelRequired":false,"title":"868"}],"softCurrencyFee":500,"hardCurrencyFee":0,"unlockLevel":1,"iap":"","resultItem":1596},"72":{"id":72,"category":"equipment","ingridients":[{"itemId":865,"ratio":1.0,"quantity":18,"maxLevelRequired":false,"title":"865"},{"itemId":869,"ratio":1.0,"quantity":18,"maxLevelRequired":false,"title":"869"}],"softCurrencyFee":500,"hardCurrencyFee":0,"unlockLevel":1,"iap":"","resultItem":1597},"73":{"id":73,"category":"equipment","ingridients":[{"itemId":866,"ratio":1.0,"quantity":18,"maxLevelRequired":false,"title":"866"},{"itemId":869,"ratio":1.0,"quantity":18,"maxLevelRequired":false,"title":"869"}],"softCurrencyFee":500,"hardCurrencyFee":0,"unlockLevel":1,"iap":"","resultItem":1598},"74":{"id":74,"category":"equipment","ingridients":[{"itemId":867,"ratio":1.0,"quantity":18,"maxLevelRequired":false,"title":"867"},{"itemId":868,"ratio":1.0,"quantity":18,"maxLevelRequired":false,"title":"868"}],"softCurrencyFee":500,"hardCurrencyFee":0,"unlockLevel":1,"iap":"","resultItem":1600},"75":{"id":75,"category":"equipment","ingridients":[{"itemId":865,"ratio":1.0,"quantity":18,"maxLevelRequired":false,"title":"865"},{"itemId":868,"ratio":1.0,"quantity":18,"maxLevelRequired":false,"title":"868"}],"softCurrencyFee":500,"hardCurrencyFee":0,"unlockLevel":1,"iap":"","resultItem":1601},"76":{"id":76,"category":"equipment","ingridients":[{"itemId":867,"ratio":1.0,"quantity":18,"maxLevelRequired":false,"title":"867"},{"itemId":868,"ratio":1.0,"quantity":18,"maxLevelRequired":false,"title":"868"}],"softCurrencyFee":500,"hardCurrencyFee":0,"unlockLevel":1,"iap":"","resultItem":1602},"77":{"id":77,"category":"equipment","ingridients":[{"itemId":866,"ratio":1.0,"quantity":18,"maxLevelRequired":false,"title":"866"},{"itemId":869,"ratio":1.0,"quantity":18,"maxLevelRequired":false,"title":"869"}],"softCurrencyFee":500,"hardCurrencyFee":0,"unlockLevel":1,"iap":"","resultItem":1604}}